steinnews/__init__.py
steinnews/exceptions.py
steinnews/patterns.py
steinnews-1.6.0.dist-info/LICENSE
steinnews-1.6.0.dist-info/METADATA
steinnews-1.6.0.dist-info/WHEEL
steinnews-1.6.0.dist-info/entry_points.txt
steinnews-1.6.0.dist-info/top_level.txt
steinnews-1.6.0.dist-info/RECORD
